frontend/__init__.py
frontend/components.py
frontend/config.py
frontend/dispatcher.py
frontend/dom.py
frontend/server.py
frontend/utils.py
frontend/async_utils/__init__.py
frontend/async_utils/debouncer.py
frontend/async_utils/later.py
frontend/events/__init__.py
frontend/events/clipboard.py
frontend/events/event_mixins.py
frontend/events/hash_change.py
frontend/events/ui/__init__.py
frontend/events/ui/focus.py
frontend/events/ui/input.py
frontend/events/ui/keyboard.py
frontend/events/ui/ui.py
frontend/events/ui/mouse/__init__.py
frontend/events/ui/mouse/drag.py
frontend/events/ui/mouse/mouse.py
frontend/events/ui/mouse/wheel.py
frontend-0.0.3.dist-info/LICENSE
frontend-0.0.3.dist-info/METADATA
frontend-0.0.3.dist-info/WHEEL
frontend-0.0.3.dist-info/top_level.txt
frontend-0.0.3.dist-info/RECORD
