Metadata-Version: 2.1
Name: frontend
Version: 0.0.3
Summary: Develop complex & beautiful UI frontends using Python!
Home-page: https://github.com/AgarwalPragy/frontend
Author: Pragy Agarwal
Author-email: agar.pragy@gmail.com
License: GNU GENERAL PUBLIC LICENSE
Platform: UNKNOWN
Classifier: Development Status :: 2 - Pre-Alpha
Classifier: Environment :: Web Environment
Classifier: Programming Language :: Python :: 3
Classifier: Programming Language :: Python :: 3.8
Classifier: Operating System :: OS Independent
Classifier: License :: OSI Approved :: GNU General Public License v3 or later (GPLv3+)
Classifier: Natural Language :: English
Requires-Python: >=3.8
